homeassistant2xlsx/__init__.py
homeassistant2xlsx/__main__.py
homeassistant2xlsx-1.2.2.dist-info/LICENSE
homeassistant2xlsx-1.2.2.dist-info/METADATA
homeassistant2xlsx-1.2.2.dist-info/WHEEL
homeassistant2xlsx-1.2.2.dist-info/entry_points.txt
homeassistant2xlsx-1.2.2.dist-info/RECORD
