Metadata-Version: 2.1
Name: homeassistant2xlsx
Version: 1.2.2
Summary: Add Home Assistant Data to Excel
License: MIT
Author: c0fec0de
Author-email: c0fec0de@gmail.com
Requires-Python: >=3.7.2,<4.0.0
Classifier: License :: OSI Approved :: MIT License
Classifier: Operating System :: OS Independent
Classifier: Programming Language :: Python :: 3
Classifier: Programming Language :: Python :: 3.8
Classifier: Programming Language :: Python :: 3.9
Classifier: Programming Language :: Python :: 3.10
Classifier: Programming Language :: Python :: 3.11
Classifier: Programming Language :: Python :: 3.12
Requires-Dist: openpyxl (>=3.1.2,<4.0.0)
Requires-Dist: requests (>=2.31.0,<3.0.0)
